[
    {"s":"HTML","clr1":"#762900","clr2":"orange"},
    {"s":"CSS","clr1":"blue","clr2":"green"},
    {"s":"Sass/Scss","clr1":"pink","clr2":"purple"},
    {"s":"Bootstrap 5","clr1":"purple","clr2":"#4000ff"},
    {"s":"W3.css","clr1":"#00ff78","clr2":"green"},
    {"s":"JavaScript","clr1":"#ff4900","clr2":"yellow"},
    {"s":"TypeScript","clr1":"#3178c6","clr2":"#083061"},
    {"s":"JQuery","clr1":"#0868ac","clr2":"#131b28"},
    {"s":"JSON","clr1":"#969696","clr2":"#222222"},
    {"s":"AJAX","clr1":"#2284c6","clr2":"#4a98ce"},
    {"s":"Vue.js","clr1":"green","clr2":"black"},
    {"s":"React.js","clr1":"#61d9fc","clr2":"#2b2c30"},
    {"s":"AngularJS","clr1":"red","clr2":"white"},
    {"s":"Python","clr1":"yellow","clr2":"blue"},
    {"s":"Flask","clr1":"blue","clr2":"black"},
    {"s":"PHP","clr1":"#4f5b93","clr2":"white"},
    {"s":"C/C++","clr1":"#0868ac","clr2":"white"},
    {"s":"Git (Github)","clr1":"#e84e31","clr2":"#3c2b00"},
    {"s":"SQL","clr1":"gold","clr2":"blue"},
    {"s":"UI/UX Design","clr1":"green","clr2":"black"},
    {"s":"Figma","clr1":"#f24e1e","clr2":"#ff7262"},
    {"s":"English (B2)","clr1":"red","clr2":"blue"},
    {"s":"Microsoft apps","clr1":"#f25022","clr2":"#ffb900"},
    {"s":"Algorithms","clr1":"yellow","clr2":"green"},
    {"s":"Data structures","clr1":"white","clr2":"blue"},
    {"s":"Agile Methodology","clr1":"blue","clr2":"orange"}
]